[
  {
    "id": "main",
    "components": [
      "section"
    ]
  },
  {
    "id": "columns",
    "components": []
  },
  {
    "id": "column",
    "components": [
      "text",
      "image",
      "button",
      "title",
      "blockquote"
    ]
  },
  {
    "id": "section",
    "components": [
      "text",
      "image",
      "button",
      "title",
      "hero",
      "cards",
      "columns",
      "blockquote"
    ]
  },
  {
    "id": "cards",
    "components": [
      "card"
    ]
  }
]
